    {
      "version": 4,
      "configurePresets": [
        {
          "name": "default-debug",
          "displayName": "Default Debug Build",
          "description": "Configures a debug build with default options.",
          "generator": "Ninja",
          "binaryDir": "${sourceDir}/build/debug",
          "cacheVariables": {
            "CMAKE_BUILD_TYPE": "Debug"
          }
        },
        {
          "name": "default-release",
          "displayName": "Default Release Build",
          "description": "Configures a release build with default options.",
          "generator": "Ninja",
          "binaryDir": "${sourceDir}/build/release",
          "cacheVariables": {
            "CMAKE_BUILD_TYPE": "Release"
          }
        }
      ]
    }